Workbook

Sheet summary
A1: store_name | B1: Location Results | C1: Total User Reviews | D1: Weighted Average Rating | E1: Straight Average Rating | F1: Standard Deviation
A2: Walmart | B2: =COUNTIFS(raw_data!A:A,A2) -> 2250 | C2: =SUMIFS(raw_data!F:F,raw_data!A:A,A2) -> 5430943 | D2: =SUMIFS(raw_data!G:G,raw_data!A:A,A2)/SUMIFS(raw_data!F:F,raw_data!A:A,A2) -> 3.8668229 | E2: =AVERAGEIFS(raw_data!E:E,raw_data!A:A,A2) -> 3.8710093
A3: Shaw's | B3: =COUNTIFS(raw_data!A:A,A3) -> 120 | C3: =SUMIFS(raw_data!F:F,raw_data!A:A,A3) -> 41831 | D3: =SUMIFS(raw_data!G:G,raw_data!A:A,A3)/SUMIFS(raw_data!F:F,raw_data!A:A,A3) -> 4.0072889 | E3: =AVERAGEIFS(raw_data!E:E,raw_data!A:A,A3) -> 3.9841667
A4: ACME Markets | B4: =COUNTIFS(raw_data!A:A,A4) -> 160 | C4: =SUMIFS(raw_data!F:F,raw_data!A:A,A4) -> 78484 | D4: =SUMIFS(raw_data!G:G,raw_data!A:A,A4)/SUMIFS(raw_data!F:F,raw_data!A:A,A4) -> 4.0287205 | E4: =AVERAGEIFS(raw_data!E:E,raw_data!A:A,A4) -> 3.991875
A5: Safeway | B5: =COUNTIFS(raw_data!A:A,A5) -> 878 | C5: =SUMIFS(raw_data!F:F,raw_data!A:A,A5) -> 707002 | D5: =SUMIFS(raw_data!G:G,raw_data!A:A,A5)/SUMIFS(raw_data!F:F,raw_data!A:A,A5) -> 4.044334 | E5: =AVERAGEIFS(raw_data!E:E,raw_data!A:A,A5) -> 4.0465831
A6: Stop & Shop | B6: =COUNTIFS(raw_data!A:A,A6) -> 344 | C6: =SUMIFS(raw_data!F:F,raw_data!A:A,A6) -> 188070 | D6: =SUMIFS(raw_data!G:G,raw_data!A:A,A6)/SUMIFS(raw_data!F:F,raw_data!A:A,A6) -> 4.0745579 | E6: =AVERAGEIFS(raw_data!E:E,raw_data!A:A,A6) -> 4.047093
A7: King Soopers | B7: =COUNTIFS(raw_data!A:A,A7) -> 93 | C7: =SUMIFS(raw_data!F:F,raw_data!A:A,A7) -> 52087 | D7: =SUMIFS(raw_data!G:G,raw_data!A:A,A7)/SUMIFS(raw_data!F:F,raw_data!A:A,A7) -> 4.0786473 | E7: =AVERAGEIFS(raw_data!E:E,raw_data!A:A,A7) -> 4.0731183
A8: Save-A-Lot | B8: =COUNTIFS(raw_data!A:A,A8) -> 1037 | C8: =SUMIFS(raw_data!F:F,raw_data!A:A,A8) -> 357887 | D8: =SUMIFS(raw_data!G:G,raw_data!A:A,A8)/SUMIFS(raw_data!F:F,raw_data!A:A,A8) -> 4.1060888 | E8: =AVERAGEIFS(raw_data!E:E,raw_data!A:A,A8) -> 4.1379344
A9: Jewel-Osco | B9: =COUNTIFS(raw_data!A:A,A9) -> 174 | C9: =SUMIFS(raw_data!F:F,raw_data!A:A,A9) -> 130501 | D9: =SUMIFS(raw_data!G:G,raw_data!A:A,A9)/SUMIFS(raw_data!F:F,raw_data!A:A,A9) -> 4.1226358 | E9: =AVERAGEIFS(raw_data!E:E,raw_data!A:A,A9) -> 4.1396552
A10: Giant Eagle | B10: =COUNTIFS(raw_data!A:A,A10) -> 210 | C10: =SUMIFS(raw_data!F:F,raw_data!A:A,A10) -> 153626 | D10: =SUMIFS(raw_data!G:G,raw_data!A:A,A10)/SUMIFS(raw_data!F:F,raw_data!A:A,A10) -> 4.1403714 | E10: =AVERAGEIFS(raw_data!E:E,raw_data!A:A,A10) -> 4.0966667
A11: Kroger | B11: =COUNTIFS(raw_data!A:A,A11) -> 906 | C11: =SUMIFS(raw_data!F:F,raw_data!A:A,A11) -> 481392 | D11: =SUMIFS(raw_data!G:G,raw_data!A:A,A11)/SUMIFS(raw_data!F:F,raw_data!A:A,A11) -> 4.1547317 | E11: =AVERAGEIFS(raw_data!E:E,raw_data!A:A,A11) -> 4.15
A12: Fred Meyer | B12: =COUNTIFS(raw_data!A:A,A12) -> 69 | C12: =SUMIFS(raw_data!F:F,raw_data!A:A,A12) -> 64631 | D12: =SUMIFS(raw_data!G:G,raw_data!A:A,A12)/SUMIFS(raw_data!F:F,raw_data!A:A,A12) -> 4.1588077 | E12: =AVERAGEIFS(raw_data!E:E,raw_data!A:A,A12) -> 4.1507246
A13: Food 4 Less | B13: =COUNTIFS(raw_data!A:A,A13) -> 146 | C13: =SUMIFS(raw_data!F:F,raw_data!A:A,A13) -> 97677 | D13: =SUMIFS(raw_data!G:G,raw_data!A:A,A13)/SUMIFS(raw_data!F:F,raw_data!A:A,A13) -> 4.1696582 | E13: =AVERAGEIFS(raw_data!E:E,raw_data!A:A,A13) -> 4.1263889
... A42: Trader Joe's | B42: =COUNTIFS(raw_data!A:A,A42) -> 512 | C42: =SUMIFS(raw_data!F:F,raw_data!A:A,A42) -> 608643 | D42: =SUMIFS(raw_data!G:G,raw_data!A:A,A42)/SUMIFS(raw_data!F:F,raw_data!A:A,A42) -> 4.6192625 | E42: =AVERAGEIFS(raw_data!E:E,raw_data!A:A,A42) -> 4.6330078

Sheet pivot table w stdev
A3: Row Labels | B3: Count of google_store_name | C3: Average of rating | D3: StdDev of rating
A4: Trader Joe's | B4: 512 | C4: 4.6330078 | D4: 0.07312119
A5: Wegmans | B5: 104 | C5: 4.6067308 | D5: 0.061160973
A6: Costco | B6: 390 | C6: 4.5182519 | D6: 0.093615953
A7: Aldi | B7: 841 | C7: 4.483293 | D7: 0.13622372
A8: Vitamin Cottage Natural Grocers | B8: 159 | C8: 4.463522 | D8: 0.11929189
A9: Fresh Market | B9: 159 | C9: 4.4436709 | D9: 0.094722891
A10: Publix | B10: 897 | C10: 4.4410256 | D10: 0.13656442
A11: HEB | B11: 215 | C11: 4.4409302 | D11: 0.19598557
A12: WinCo Foods | B12: 71 | C12: 4.4253521 | D12: 0.10917654
A13: Grocery Outlet | B13: 125 | C13: 4.4216 | D13: 0.12087317
A14: Sprouts Farmers Market | B14: 346 | C14: 4.3930636 | D14: 0.14569526
A15: Stater Bros. Markets | B15: 113 | C15: 4.379646 | D15: 0.17173448
... A45: Grand Total | B45: 15715 | C45: 4.2038927 | D45: 0.27713343

Sheet raw_data
A1: store_name | B1: google_place_id | C1: google_store_name | D1: formatted_address | E1: rating | F1: user_ratings_total | G1: weighted rating
A2: ACME Markets | B2: ChIJr3lhIr-YwokRywwNvLs4NIY | C2: ACME Markets | D2: 1261 E Putnam Ave, Riverside, CT 06878, United States | E2: 4 | F2: 112 | G2: =E2*F2 -> 448
A3: ACME Markets | B3: ChIJ13hp7jiXwokR4H_uJtTJWF0 | C3: ACME Markets | D3: 261 S Ridge St, Rye Brook, NY 10573, United States | E3: 4.1 | F3: 194 | G3: =E3*F3 -> 795.4
A4: ACME Markets | B4: ChIJb1_aXEOhwokROi1CQf1I_pI | C4: ACME Markets | D4: 1201 High Ridge Rd, Stamford, CT 06905, United States | E4: 3.5 | F4: 278 | G4: =E4*F4 -> 973
A5: ACME Markets | B5: ChIJuR2pMDaYwokRb0XP3Kp9Yjk | C5: ACME Markets | D5: 160 West Putnam Avenue, Greenwich, CT 06830, United States | E5: 4 | F5: 180 | G5: =E5*F5 -> 720
A6: ACME Markets | B6: ChIJN5dighCnwokR9GleLHJbLbQ | C6: ACME Markets | D6: 288 Elm St, New Canaan, CT 06840, United States | E6: 4.1 | F6: 162 | G6: =E6*F6 -> 664.2
A7: ACME Markets | B7: ChIJcZ4UY9YAx4kR2PBiFtBJ6DQ | C7: ACME Markets | D7: 1 University Dr, Newark, DE 19702, United States | E7: 3.9 | F7: 645 | G7: =E7*F7 -> 2515.5
A8: ACME Markets | B8: ChIJZUDDSBaqx4kRoZ9UM3zk9C0 | C8: ACME Markets | D8: 100 College Square, Newark, DE 19711, United States | E8: 3.9 | F8: 730 | G8: =E8*F8 -> 2847
A9: ACME Markets | B9: ChIJx8AOaGSpx4kRxqXUaq__iZQ | C9: ACME Markets | D9: 100 Suburban Dr, Newark, DE 19711, United States | E9: 4.1 | F9: 566 | G9: =E9*F9 -> 2320.6
A10: ACME Markets | B10: ChIJV8rUYB8Ax4kR04s4db1B5_M | C10: ACME Markets | D10: 4720 Limestone Rd, Wilmington, DE 19808, United States | E10: 4.2 | F10: 373 | G10: =E10*F10 -> 1566.6
A11: ACME Markets | B11: ChIJvfkeEMUBx4kR6StmNBVg0xI | C11: ACME Markets | D11: 4365 Robert, Kirkwood Hwy, Wilmington, DE 19808, United States | E11: 3.9 | F11: 634 | G11: =E11*F11 -> 2472.6
A12: ACME Markets | B12: ChIJt3LAg_8Bx4kR8k09uSDQBYA | C12: ACME Markets | D12: 1308 Centerville Rd, Wilmington, DE 19808, United States | E12: 4.1 | F12: 998 | G12: =E12*F12 -> 4091.8
A13: ACME Markets | B13: ChIJ3duatDlxx4kRvdsdCBvr9zc | C13: ACME Markets | D13: 236 E Glenwood Ave, Smyrna, DE 19977, United States | E13: 3.9 | F13: 516 | G13: =E13*F13 -> 2012.4
... A601: Aldi | B601: ChIJfSg2EjeEk4cRRvhdMGY47lo | C601: ALDI | D601: 3135 Manawa Center Dr, Council Bluffs, IA 51501, United States | E601: 4.5 | F601: 780 | G601: =E601*F601 -> 3510
A602: Aldi | B602: ChIJt1ueM1YD44cR03UT45mmxaw | C602: Aldi | D602: 907 W Platt St, Maquoketa, IA 52060, United States | G602: =E602*F602 -> 0
A603: Aldi | B603: ChIJw5t3-sRB5IcRzbc5FEa3pLw | C603: Aldi | D603: 1534 S Gilbert St, Iowa City, IA 52240, United States | E603: 4.5 | F603: 2 | G603: =E603*F603 -> 9
A604: Aldi | B604: ChIJg8vlvvny5IcRk9IaiEz9JmQ | C604: ALDI | D604: 1001 50th St, Marion, IA 52302, United States | E604: 4.6 | F604: 649 | G604: =E604*F604 -> 2985.4
A605: Aldi | B605: ChIJEwztgIX65IcRxQ7Zjkl0GKg | C605: ALDI | D605: 5425 Blairs Forest Blvd NE, Cedar Rapids, IA 52402, United States | E605: 4.5 | F605: 891 | G605: =E605*F605 -> 4009.5
A606: Aldi | B606: ChIJYwJgnAn55IcR4YoA1cobq30 | C606: ALDI | D606: 1860 Edgewood Rd SW, Cedar Rapids, IA 52404, United States | E606: 4.5 | F606: 877 | G606: =E606*F606 -> 3946.5
A607: Aldi | B607: ChIJA-qDpt8d5ocRJByHGCsGq_M | C607: ALDI | D607: 940 N Quincy Ave, Ottumwa, IA 52501, United States | E607: 4.5 | F607: 357 | G607: =E607*F607 -> 1606.5
A608: Aldi | B608: ChIJyew6aZfx6IcRI5Aiv0r07tI | C608: ALDI | D608: 215 S Main St, Centerville, IA 52544, United States | E608: 4.6 | F608: 326 | G608: =E608*F608 -> 1499.6
A609: Aldi | B609: ChIJbzSbpiMy4YcRNVUS701PZis | C609: ALDI | D609: 3135 E Agency St, Burlington, IA 52601, United States | E609: 4.6 | F609: 492 | G609: =E609*F609 -> 2263.2
A610: Aldi | B610: ChIJbxUUwm_J5ocR0_N0vwFTIGo | C610: ALDI | D610: 927 Ave G, Fort Madison, IA 52627, United States | E610: 4.5 | F610: 319 | G610: =E610*F610 -> 1435.5
A611: Aldi | B611: ChIJc8LoJao754cRiHhBe9kuFZk | C611: ALDI | D611: 3379 Main St, Keokuk, IA 52632, United States | E611: 4.6 | F611: 209 | G611: =E611*F611 -> 961.4
A612: Aldi | B612: ChIJA6M1aZWh5ocRZZdJel-4UG4 | C612: ALDI | D612: 1309 E Washington St, Mt Pleasant, IA 52641, United States | E612: 4.5 | F612: 257 | G612: =E612*F612 -> 1156.5
A613: Aldi | B613: ChIJL_HfDuxm4ocRht8AQQvbilA | C613: ALDI | D613: 2575 Lincoln Way, Clinton, IA 52732, United States | E613: 4.5 | F613: 295 | G613: =E613*F613 -> 1327.5
A614: Aldi | B614: ChIJa9_mYgrv44cRtKUZafE2xHg | C614: ALDI | D614: 3200 N Port Dr, Muscatine, IA 52761, United States | E614: 4.6 | F614: 555 | G614: =E614*F614 -> 2553
... A623: Aldi | B623: ChIJx0HgBHnID4gRCvE9Eueo80k | C623: ALDI | D623: 7905 Golf Rd, Morton Grove, IL 60053, United States | E623: 4.4 | F623: 455 | G623: =E623*F623 -> 2002
A624: Aldi | B624: ChIJe1UE9PC5D4gRX7QAsi4bRxE | C624: Aldi | D624: 730 E Rand Rd, Mt Prospect, IL 60056, United States | G624: =E624*F624 -> 0
A625: Aldi | B625: ChIJ2zr7XS6YD4gRABABXL25I-U | C625: ALDI | D625: 730 S Illinois 83, Mundelein, IL 60060, United States | E625: 4.6 | F625: 550 | G625: =E625*F625 -> 2530
A626: Aldi | B626: ChIJSxfttbK7D4gRNGILdMOgwHg | C626: ALDI | D626: 1432 E Rand Rd, Prospect Heights, IL 60070, United States | E626: 4.5 | F626: 377 | G626: =E626*F626 -> 1696.5
A627: Aldi | B627: ChIJO3w6mayED4gR_CpNd_PJHhs | C627: ALDI | D627: 74 W Rollins Rd, Round Lake Beach, IL 60073, United States | E627: 4.4 | F627: 1012 | G627: =E627*F627 -> 4452.8
A628: Aldi | B628: ChIJ09OFhBrPD4gR2IB9P3WRkPY | C628: ALDI | D628: 4833 Oakton St, Skokie, IL 60077, United States | E628: 4.4 | F628: 681 | G628: =E628*F628 -> 2996.4
A629: Aldi | B629: ChIJvyccNe6SD4gRK-hA6EsjFNU | C629: ALDI | D629: 1050 S Waukegan Rd, Waukegan, IL 60085, United States | E629: 4.4 | F629: 448 | G629: =E629*F629 -> 1971.2
A630: Aldi | B630: ChIJxTJQ53-7D4gRLB-ZUs18iR0 | C630: ALDI | D630: 1202 W Dundee Rd, Buffalo Grove, IL 60089, United States | E630: 4.4 | F630: 604 | G630: =E630*F630 -> 2657.6
A631: Aldi | B631: ChIJMxhnXge8D4gRm4Pf3gZfbjk | C631: Aldi | D631: 901 W Dundee Rd, Wheeling, IL 60090, United States | E631: 5 | F631: 1 | G631: =E631*F631 -> 5
A632: Aldi | B632: ChIJG30n53tpD4gRC0uR6a4rLZE | C632: ALDI | D632: 410 S Eastwood Dr, Woodstock, IL 60098, United States | E632: 4.5 | F632: 314 | G632: =E632*F632 -> 1413
A633: Aldi | B633: ChIJkTOcs3rzD4gRU26DFlN-GZ4 | C633: ALDI | D633: 2861 Sheridan Rd, Zion, IL 60099, United States | E633: 4.5 | F633: 576 | G633: =E633*F633 -> 2592
A634: Aldi | B634: ChIJQYXRPG4SD4gR55Yvrr6eA_M | C634: ALDI | D634: 425 S Randall Rd, Algonquin, IL 60102, United States | E634: 4.5 | F634: 330 | G634: =E634*F634 -> 1485
A635: Aldi | B635: ChIJB4IoX8NKDogRt_qvRMadkMA | C635: ALDI | D635: 400 S Mannheim Rd, Bellwood, IL 60104, United States | E635: 4.3 | F635: 549 | G635: =E635*F635 -> 2360.7
A636: Aldi | B636: ChIJr81B89upD4gR9s23WPAQer8 | C636: ALDI | D636: 913 E Irving Park Rd, Streamwood, IL 60107, United States | E636: 4.3 | F636: 699 | G636: =E636*F636 -> 3005.7
... A704: Aldi | B704: ChIJeXUOE83TD4gR2aY-FrI5uew | C704: ALDI | D704: 4500 N Broadway, Chicago, IL 60640, United States | E704: 4.4 | F704: 938 | G704: =E704*F704 -> 4127.2
A705: Aldi | B705: ChIJm96LNK_ND4gRUlUfW7Ii6n8 | C705: Aldi | D705: 3363 N Milwaukee Ave, Chicago, IL 60641, United States | G705: =E705*F705 -> 0
A706: Aldi | B706: ChIJtex4QkYkDogRtKHDPdcfNCA | C706: ALDI | D706: 821 W 115th St, Chicago, IL 60643, United States | E706: 4.3 | F706: 500 | G706: =E706*F706 -> 2150
A707: Aldi | B707: ChIJlbqUjr7SD4gRGjWaiksfsyc | C707: ALDI | D707: 1753 N Milwaukee Ave, Chicago, IL 60647, United States | E707: 4.6 | F707: 1169 | G707: =E707*F707 -> 5377.4
A708: Aldi | B708: ChIJ7-1yTq0yDogRFNj2BYzT6aA | C708: ALDI | D708: 800 N Kedzie Ave, Chicago, IL 60651, United States | E708: 4.2 | F708: 420 | G708: =E708*F708 -> 1764
A709: Aldi | B709: ChIJA4h9boEwDogRwiHTO8k05P8 | C709: ALDI | D709: 8333 S Cicero Ave, Chicago, IL 60652, United States | E709: 4.4 | F709: 810 | G709: =E709*F709 -> 3564
A710: Aldi | B710: ChIJCT7FoR_OD4gRkGJEAiftYOA | C710: ALDI | D710: 6220 N California Ave, Chicago, IL 60659, United States | E710: 4.4 | F710: 921 | G710: =E710*F710 -> 4052.4
A711: Aldi | B711: ChIJl8jkMy_JD4gRKd0TumniuME | C711: ALDI | D711: 6250 W Touhy Ave, Niles, IL 60714, United States | E711: 4.5 | F711: 785 | G711: =E711*F711 -> 3532.5
A712: Aldi | B712: ChIJTa65LGo7DogRD6HW7bi24YQ | C712: ALDI | D712: 12050 S Pulaski Rd, Alsip, IL 60803, United States | E712: 4.4 | F712: 353 | G712: =E712*F712 -> 1553.2
A713: Aldi | B713: ChIJ91aTP6wzDogR4AVNlSPUsZk | C713: ALDI | D713: 4630 W Cermak Rd, Cicero, IL 60804, United States | E713: 4.4 | F713: 909 | G713: =E713*F713 -> 3999.6
A714: Aldi | B714: ChIJzZjsfak6DogRhhqwZMpdzH8 | C714: ALDI | D714: 3231 W 87th St, Evergreen Park, IL 60805, United States | E714: 4.5 | F714: 413 | G714: =E714*F714 -> 1858.5
A715: Aldi | B715: ChIJ7aLQNH4jDogRE_jaA2mE5Nw | C715: ALDI | D715: 13085 S Ashland Ave, Calumet Park, IL 60827, United States | E715: 4.3 | F715: 595 | G715: =E715*F715 -> 2558.5
A716: Aldi | B716: ChIJXQrYwVzdDYgRJFO6FAWsufU | C716: Aldi | D716: 370 S Schuyler Ave, Kankakee, IL 60901, United States | G716: =E716*F716 -> 0
A717: Aldi | B717: ChIJq_DXtF3nDYgRM-pYgNzOjrM | C717: ALDI | D717: 2051 N State Rte 50, Bourbonnais, IL 60914, United States | E717: 4.5 | F717: 534 | G717: =E717*F717 -> 2403
A718: Aldi | B718: ChIJz9JdfMy1CIgRoCCSpH71TYo | C718: ALDI | D718: 1021 N State St, Belvidere, IL 61008, United States | E718: 4.5 | F718: 733 | G718: =E718*F718 -> 3298.5
A719: Aldi | B719: ChIJERT08kasCYgR6hi08MDldFM | C719: Aldi | D719: 1387 N Galena Ave, Dixon, IL 61021, United States | G719: =E719*F719 -> 0
A720: Aldi | B720: ChIJrdeCrtZrCIgRPDZGBl7FIkw | C720: ALDI | D720: 726 W South St, Freeport, IL 61032, United States | E720: 4.5 | F720: 633 | G720: =E720*F720 -> 2848.5
A721: Aldi | B721: ChIJpzw_Cr3fCIgRqM2Ipmye7gQ | C721: ALDI | D721: 1251 N 7th St, Rochelle, IL 61068, United States | E721: 4.4 | F721: 357 | G721: =E721*F721 -> 1570.8
A722: Aldi | B722: ChIJ86KuYvC2CYgR8kJgG2qpWww | C722: ALDI | D722: 3409 E Lincolnway, Sterling, IL 61081, United States | E722: 4.5 | F722: 528 | G722: =E722*F722 -> 2376
A723: Aldi | B723: ChIJjeuJxr6VCIgRgxoklNsIre4 | C723: ALDI | D723: 3831 Auburn St, Rockford, IL 61101, United States | E723: 4.3 | F723: 530 | G723: =E723*F723 -> 2279
A724: Aldi | B724: ChIJB76J5fy4CIgRdzNZtMbf3dA | C724: ALDI | D724: 6650 E State St, Rockford, IL 61108, United States | E724: 4.5 | F724: 916 | G724: =E724*F724 -> 4122
A725: Aldi | B725: ChIJxw9e8YG_CIgROQZO6HUc0oQ | C725: ALDI | D725: 2680 20th St, Rockford, IL 61109, United States | E725: 4.4 | F725: 882 | G725: =E725*F725 -> 3880.8
A726: Aldi | B726: ChIJpYh88tO9CIgRvf3E0bhPBFc | C726: ALDI | D726: 5910 N 2nd St, Loves Park, IL 61111, United States | E726: 4.5 | F726: 619 | G726: =E726*F726 -> 2785.5
A727: Aldi | B727: ChIJuU8K4Ju8CIgRxmS3HEWO-iA | C727: ALDI | D727: 1545 West Lane Rd, Machesney Park, IL 61115, United States | E727: 4.5 | F727: 534 | G727: =E727*F727 -> 2403
A728: Aldi | B728: ChIJ_zSHurkz4ocRMyViJPGRAdU | C728: ALDI | D728: 1880 38th St, Rock Island, IL 61201, United States | E728: 4.6 | F728: 847 | G728: =E728*F728 -> 3896.2
A729: Aldi | B729: ChIJ62Z0JvAw4ocRgvWa1dgef18 | C729: ALDI | D729: 4211 Avenue of the Cities, Moline, IL 61265, United States | E729: 4.6 | F729: 610 | G729: =E729*F729 -> 2806
A730: Aldi | B730: ChIJsaGGcJpTCYgR9B1xsYIeawk | C730: ALDI | D730: 2710 Columbus St, Ottawa, IL 61350, United States | E730: 4.5 | F730: 339 | G730: =E730*F730 -> 1525.5
A731: Aldi | B731: ChIJIxrThsFgCYgR5HzTFvx7EA8 | C731: ALDI | D731: 951 Shooting Park Rd, Peru, IL 61354, United States | E731: 4.6 | F731: 556 | G731: =E731*F731 -> 2557.6
... A737: Aldi | B737: ChIJz__SKy7xCogR1B7Fss8nYu4 | C737: ALDI | D737: 3475 Court St, Pekin, IL 61554, United States | E737: 4.6 | F737: 380 | G737: =E737*F737 -> 1748
A738: Aldi | B738: ChIJMy7Sew9cCogRPs9--mt-Ah0 | C738: Aldi | D738: 3116 N Sterling Ave, Peoria, IL 61604, United States | G738: =E738*F738 -> 0
A739: Aldi | B739: ChIJbUGGXDJZCogRA6oVH9S9ZD8 | C739: ALDI | D739: 210 South Western Avenue, Peoria, IL 61605, United States | E739: 3 | F739: 2 | G739: =E739*F739 -> 6
A740: Aldi | B740: ChIJu51QxVRYCogRpNdDLlRhYX4 | C740: ALDI | D740: 251 Clock Tower Dr, East Peoria, IL 61611, United States | E740: 4.6 | F740: 571 | G740: =E740*F740 -> 2626.6
A741: Aldi | B741: ChIJndcCne5bCogRnZoc85Y0CM8 | C741: ALDI | D741: 3420 N University St, Peoria, IL 61604, United States | E741: 4.5 | F741: 940 | G741: =E741*F741 -> 4230
A742: Aldi | B742: ChIJTWSv_j9yC4gRXw7NvsMFXkA | C742: ALDI | D742: 907 Maple Hill Rd, Bloomington, IL 61705, United States | E742: 4.5 | F742: 589 | G742: =E742*F742 -> 2650.5
A743: Aldi | B743: ChIJT3YfdI9wC4gR58rPK5Ok14g | C743: ALDI | D743: 301 Greenbriar Dr, Normal, IL 61761, United States | E743: 4.6 | F743: 722 | G743: =E743*F743 -> 3321.2
A744: Aldi | B744: ChIJE6QYzSByDIgRZ5A359VLpng | C744: ALDI | D744: 701 Rittenhouse Dr, Pontiac, IL 61764, United States | E744: 4.5 | F744: 217 | G744: =E744*F744 -> 976.5
A745: Aldi | B745: ChIJa6vLxh4oDYgRaxFhCMkxCUg | C745: ALDI | D745: 3102 E University Ave, Urbana, IL 61802, United States | E745: 4.6 | F745: 474 | G745: =E745*F745 -> 2180.4
A746: Aldi | B746: ChIJAcHxlhbaDIgRjv037oQfmwA | C746: ALDI | D746: 801 West Interstate Dr, Champaign, IL 61822, United States | E746: 4.6 | F746: 1133 | G746: =E746*F746 -> 5211.8
A747: Aldi | B747: ChIJMaYt7AhaDYgRKkaDF8Xofig | C747: ALDI | D747: 502 S Gilbert St, Danville, IL 61832, United States | E747: 4.5 | F747: 981 | G747: =E747*F747 -> 4414.5
A748: Aldi | B748: ChIJ7YQExAUQc4gRIsTpTZ6LsNE | C748: ALDI | D748: 1220 Fort Worth Way, Mattoon, IL 61938, United States | E748: 4.5 | F748: 288 | G748: =E748*F748 -> 1296
A749: Aldi | B749: ChIJdcnsGbJc34cRG5zMhxHMhtg | C749: ALDI | D749: 2822 Homer Adams Pkwy, Alton, IL 62002, United States | E749: 4.6 | F749: 804 | G749: =E749*F749 -> 3698.4
A750: Aldi | B750: ChIJ7yLHJQn5dYgRBYwxREh6WtE | C750: ALDI | D750: 16 Cottonwood Rd, Glen Carbon, IL 62034, United States | E750: 4.6 | F750: 718 | G750: =E750*F750 -> 3302.8
... A761: Aldi | B761: ChIJYb9tMpixdIgR7z_o8GwDv-4 | C761: ALDI | D761: 510 E Pershing Rd, Decatur, IL 62526, United States | E761: 4.5 | F761: 691 | G761: =E761*F761 -> 3109.5
A762: Aldi | B762: ChIJq9UCdDnkdIgR1XnNZp6tUM4 | C762: Aldi | D762: 201 W Vine St, Taylorville, IL 62568, United States | G762: =E762*F762 -> 0
A763: Aldi | B763: ChIJRT368ffr34cR1keyUFw1s84 | C763: ALDI | D763: 329 E Morton Ave, Jacksonville, IL 62650, United States | E763: 4.5 | F763: 615 | G763: =E763*F763 -> 2767.5
A764: Aldi | B764: ChIJ9VYzZgnYCogRWgM57tcc2PM | C764: ALDI | D764: 2500 Woodlawn Rd, Lincoln, IL 62656, United States | E764: 4.5 | F764: 200 | G764: =E764*F764 -> 900
A765: Aldi | B765: ChIJg4RjTt85dYgRh3w60VPqrIY | C765: Aldi | D765: 1150 N 5th St, Springfield, IL 62702, United States | G765: =E765*F765 -> 0
A766: Aldi | B766: ChIJGxgIN0NHdYgRffpx_91TAHw | C766: ALDI | D766: 3425 Freedom Dr, Springfield, IL 62704, United States | E766: 4.5 | F766: 353 | G766: =E766*F766 -> 1588.5
A767: Aldi | B767: ChIJYToSQuggdIgRLArNRRkzFB0 | C767: ALDI | D767: 300 Aaron Pkwy, Centralia, IL 62801, United States | E767: 4.6 | F767: 275 | G767: =E767*F767 -> 1265
A768: Aldi | B768: ChIJUSx74vy3dogRBlI9pNMx1SE | C768: ALDI | D768: 201 South Davidson Ave, Mt Vernon, IL 62864, United States | E768: 4.5 | F768: 347 | G768: =E768*F768 -> 1561.5
A769: Aldi | B769: ChIJs_vwxeIRd4gRwlN6p06xTQA | C769: Aldi | D769: 2201 W Ramada Ln, Carbondale, IL 62901, United States | G769: =E769*F769 -> 0
A770: Aldi | B770: ChIJ-Zdz9JTDcIgRUu2_VNio0Ok | C770: ALDI | D770: 740 N Commercial St, Harrisburg, IL 62946, United States | E770: 4.6 | F770: 226 | G770: =E770*F770 -> 1039.6
A771: Aldi | B771: ChIJD8GEXHU6d4gRjmNWGlRQCFc | C771: ALDI | D771: 1305 N Russell St, Marion, IL 62959, United States | E771: 4.5 | F771: 603 | G771: =E771*F771 -> 2713.5
A772: Aldi | B772: ChIJPX1vq2HXFIgRrI2NHC5p-Vc | C772: ALDI | D772: 1428 E 53rd St, Anderson, IN 46013, United States | E772: 4.5 | F772: 943 | G772: =E772*F772 -> 4243.5
A773: Aldi | B773: ChIJT8H_fZVpE4gRKcBeVfqFtE0 | C773: ALDI | D773: 2465 E Wabash St, Frankfort, IN 46041, United States | E773: 4.4 | F773: 266 | G773: =E773*F773 -> 1170.4
A774: Aldi | B774: ChIJFThYfWtPE4gRxyR7b__e43k | C774: ALDI | D774: 2465 N Lebanon St, Lebanon, IN 46052, United States | E774: 4.6 | F774: 425 | G774: =E774*F774 -> 1955
A775: Aldi | B775: ChIJNyLQVie3FIgRplXYh7YNMzk | C775: ALDI | D775: 16971 Clover Rd, Noblesville, IN 46060, United States | E775: 4.6 | F775: 740 | G775: =E775*F775 -> 3404
A776: Aldi | B776: ChIJ9_khbfavbIgRngFJ7fHHcXs | C776: ALDI | D776: 9779 E US Hwy 36, Avon, IN 46123, United States | E776: 4.6 | F776: 703 | G776: =E776*F776 -> 3233.8
A777: Aldi | B777: ChIJq_T4z7jcbIgRKOX7Mp1Y_Zs | C777: ALDI | D777: 65 Putnam Plaza, Greencastle, IN 46135, United States | E777: 4.5 | F777: 237 | G777: =E777*F777 -> 1066.5
...
